<!DOCTYPE Camera>
<Presets>
<Preset Name="manix_small">
<Film>
<Width Value="400"/>
<Height Value="500"/>
<Exposure Value="0.75"/>
</Film>
<Aperture>
<Size Value="0"/>
</Aperture>
<Projection>
<FieldOfView Value="35"/>
</Projection>
<Focus>
<FocalDistance Value="0.75"/>
</Focus>
<From X="-0.0572543" Y="0.481313" Z="-0.449298"/>
<Target X="0.436045" Y="0.549919" Z="0.478464"/>
<Up X="-0.295448" Y="0.777145" Z="-0.555657"/>
</Preset>
<Preset Name="bonsai_small">
<Film>
<Width Value="400"/>
<Height Value="600"/>
<Exposure Value="0.5813"/>
</Film>
<Aperture>
<Size Value="0.0062"/>
</Aperture>
<Projection>
<FieldOfView Value="35"/>
</Projection>
<Focus>
<FocalDistance Value="0.75"/>
</Focus>
<From X="-0.214269" Y="0.262453" Z="-0.43662"/>
<Target X="0.548536" Y="0.363538" Z="0.274707"/>
<Up X="-0.477882" Y="0.756994" Z="-0.445632"/>
</Preset>
<Preset Name="engine_small">
<Film>
<Width Value="400"/>
<Height Value="550"/>
<Exposure Value="0.7764"/>
</Film>
<Aperture>
<Size Value="0.0221"/>
</Aperture>
<Projection>
<FieldOfView Value="35"/>
</Projection>
<Focus>
<FocalDistance Value="0.75"/>
</Focus>
<From X="-0.607903" Y="0.31739" Z="-0.346"/>
<Target X="0.532705" Y="0.552984" Z="0.260471"/>
<Up X="-0.630843" Y="0.69966" Z="-0.335424"/>
</Preset>
<Preset Name="backpack_small">
<Film>
<Width Value="512"/>
<Height Value="512"/>
<Exposure Value="0.4553"/>
</Film>
<Aperture>
<Size Value="0"/>
</Aperture>
<Projection>
<FieldOfView Value="35"/>
</Projection>
<Focus>
<FocalDistance Value="0.75"/>
</Focus>
<From X="1.52972" Y="1.00409" Z="0.119461"/>
<Target X="0.539622" Y="0.358265" Z="0.460377"/>
<Up X="0.0593694" Y="0.998021" Z="-0.0204433"/>
</Preset>
<Preset Name="artifix_small">
<Film>
<Width Value="512"/>
<Height Value="512"/>
<Exposure Value="0.7724"/>
</Film>
<Aperture>
<Size Value="0"/>
</Aperture>
<Projection>
<FieldOfView Value="35"/>
</Projection>
<Focus>
<FocalDistance Value="0.75"/>
</Focus>
<From X="0.918336" Y="1.46746" Z="-0.552406"/>
<Target X="0.449028" Y="0.591599" Z="0.454031"/>
<Up X="-0.022112" Y="0.998611" Z="0.0474138"/>
</Preset>
<Preset Name="macoessix_small">
<Film>
<Width Value="400"/>
<Height Value="800"/>
<Exposure Value="0.0772"/>
</Film>
<Aperture>
<Size Value="0"/>
</Aperture>
<Projection>
<FieldOfView Value="35"/>
</Projection>
<Focus>
<FocalDistance Value="0.466"/>
</Focus>
<From X="-0.443925" Y="0.286852" Z="-0.280112"/>
<Target X="0.322826" Y="0.516813" Z="0.393428"/>
<Up X="-0.558001" Y="0.669608" Z="-0.490163"/>
</Preset>
<Preset Name="bonsai">
<Film>
<Width Value="800"/>
<Height Value="600"/>
<Exposure Value="600"/>
</Film>
<Aperture>
<Size Value="0"/>
</Aperture>
<Projection>
<FieldOfView Value="35"/>
</Projection>
<Focus>
<FocalDistance Value="0.75"/>
</Focus>
<From X="1" Y="1" Z="1"/>
<Target X="0" Y="0" Z="0"/>
<Up X="0" Y="0" Z="0"/>
</Preset>
<Preset Name="macoessix_noeska">
<Film>
<Width Value="400"/>
<Height Value="800"/>
<Exposure Value="800"/>
</Film>
<Aperture>
<Size Value="0"/>
</Aperture>
<Projection>
<FieldOfView Value="35"/>
</Projection>
<Focus>
<FocalDistance Value="0.75"/>
</Focus>
<From X="0.32571" Y="0.586677" Z="-0.619576"/>
<Target X="0.28611" Y="0.556702" Z="0.411265"/>
<Up X="0.0212432" Y="0.832921" Z="-0.552983"/>
</Preset>
<Preset Name="artifix_small_demo">
<Film>
<Width Value="400"/>
<Height Value="500"/>
<Exposure Value="0.7764"/>
</Film>
<Aperture>
<Size Value="0"/>
</Aperture>
<Projection>
<FieldOfView Value="35"/>
</Projection>
<Focus>
<FocalDistance Value="1.271"/>
</Focus>
<From X="0.468103" Y="0.463814" Z="-1.29932"/>
<Target X="0.419495" Y="0.505831" Z="0.464938"/>
<Up X="0.0164314" Y="0.802527" Z="-0.596394"/>
</Preset>
<Preset Name="manix_small_demo">
<Film>
<Width Value="768"/>
<Height Value="576"/>
<Exposure Value="576"/>
</Film>
<Aperture>
<Size Value="0"/>
</Aperture>
<Projection>
<FieldOfView Value="24.56"/>
</Projection>
<Focus>
<FocalDistance Value="1.864"/>
</Focus>
<From X="0.533658" Y="-0.0804129" Z="-2.13561"/>
<Target X="0.371727" Y="0.497267" Z="0.431557"/>
<Up X="0.0467273" Y="0.670143" Z="-0.740762"/>
</Preset>
</Presets>
